pyco2stats/__init__.py
pyco2stats/gaussian_mixtures.py
pyco2stats/propagate_errors.py
pyco2stats/sinclair.py
pyco2stats/stats.py
pyco2stats/visualize_mpl.py
pyco2stats/visualize_plotly.py
pyco2stats-0.1.23.dist-info/licenses/License.txt
pyco2stats-0.1.23.dist-info/METADATA
pyco2stats-0.1.23.dist-info/WHEEL
pyco2stats-0.1.23.dist-info/top_level.txt
pyco2stats-0.1.23.dist-info/RECORD
