Metadata-Version: 2.4
Name: pyco2stats
Version: 0.1.23
Summary: A package for statistical analysis and plotting in the context of CO2 data
Author-email: Maurizio Petrelli <maurizio.petrelli@unipg.it>, Marco Baroni <mbaroni96@gmail.com>, Alessandra Ariano <alessandra.ariano@dottorandi.unipg.it>, Lisa Ricci <lisa.ricci@collaboratori.unipg.it>
License: MIT License
Project-URL: Homepage, https://github.com/AIVolcanoLab/pyco2stats
Project-URL: Repository, https://github.com/AIVolcanoLab/pyco2stats
Requires-Python: >=3.10
License-File: License.txt
Requires-Dist: torch>=2.0
Requires-Dist: astropy>=7.0
Requires-Dist: numpy>=1.18.0
Requires-Dist: scipy>=1.4.0
Requires-Dist: matplotlib>=3.1.0
Requires-Dist: plotly>=6.2
Requires-Dist: kaleido
Requires-Dist: dash
Requires-Dist: dash_daq
Requires-Dist: dash-bootstrap-components
Requires-Dist: scikit-learn
Requires-Dist: statsmodels
Requires-Dist: pandas
Requires-Dist: openpyxl
Requires-Dist: ipywidgets>=8
Requires-Dist: notebook
Requires-Dist: jupyterlab
Requires-Dist: jupyterlab_widgets>=3
Dynamic: license-file
